traitsui/__init__.py
traitsui/api.py
traitsui/base_panel.py
traitsui/basic_editor_factory.py
traitsui/color_column.py
traitsui/context_value.py
traitsui/default_dock_window_theme.py
traitsui/delegating_handler.py
traitsui/dock_window_theme.py
traitsui/dockable_view_element.py
traitsui/editor.py
traitsui/editor_factory.py
traitsui/file_dialog.py
traitsui/group.py
traitsui/handler.py
traitsui/help.py
traitsui/help_template.py
traitsui/helper.py
traitsui/include.py
traitsui/instance_choice.py
traitsui/item.py
traitsui/key_bindings.py
traitsui/list_str_adapter.py
traitsui/menu.py
traitsui/message.py
traitsui/mimedata.py
traitsui/table_column.py
traitsui/table_filter.py
traitsui/tabular_adapter.py
traitsui/theme.py
traitsui/toolkit.py
traitsui/toolkit_traits.py
traitsui/tree_node.py
traitsui/tree_node_renderer.py
traitsui/ui.py
traitsui/ui_editor.py
traitsui/ui_info.py
traitsui/ui_traits.py
traitsui/undo.py
traitsui/value_tree.py
traitsui/view.py
traitsui/view_element.py
traitsui/view_elements.py
traitsui/editors/__init__.py
traitsui/editors/api.py
traitsui/editors/array_editor.py
traitsui/editors/boolean_editor.py
traitsui/editors/button_editor.py
traitsui/editors/check_list_editor.py
traitsui/editors/code_editor.py
traitsui/editors/color_editor.py
traitsui/editors/compound_editor.py
traitsui/editors/csv_list_editor.py
traitsui/editors/custom_editor.py
traitsui/editors/date_editor.py
traitsui/editors/date_range_editor.py
traitsui/editors/datetime_editor.py
traitsui/editors/default_override.py
traitsui/editors/directory_editor.py
traitsui/editors/dnd_editor.py
traitsui/editors/drop_editor.py
traitsui/editors/enum_editor.py
traitsui/editors/file_editor.py
traitsui/editors/font_editor.py
traitsui/editors/history_editor.py
traitsui/editors/html_editor.py
traitsui/editors/image_editor.py
traitsui/editors/image_enum_editor.py
traitsui/editors/instance_editor.py
traitsui/editors/key_binding_editor.py
traitsui/editors/list_editor.py
traitsui/editors/list_str_editor.py
traitsui-8.0.0.dist-info/LICENSE.txt
traitsui-8.0.0.dist-info/METADATA
traitsui-8.0.0.dist-info/WHEEL
traitsui-8.0.0.dist-info/entry_points.txt
traitsui-8.0.0.dist-info/top_level.txt
traitsui-8.0.0.dist-info/RECORD
